copious/__init__.py
copious/cv/__init__.py
copious/cv/camera_model.py
copious/cv/data_io.py
copious/cv/geometry.py
copious/cv/graphics.py
copious/data_structure/__init__.py
copious/data_structure/dict.py
copious/data_structure/list.py
copious/data_structure/set.py
copious/io/__init__.py
copious/io/args.py
copious/io/fs.py
copious/io/helper.py
copious/io/indices.py
copious/io/network.py
copious/io/parallelism.py
copious/plot/__init__.py
copious/plot/color.py
copious-0.1.32.dist-info/METADATA
copious-0.1.32.dist-info/WHEEL
copious-0.1.32.dist-info/top_level.txt
copious-0.1.32.dist-info/RECORD
