Metadata-Version: 2.4
Name: copious
Version: 0.1.32
Summary: A handy tool that make your day to day programming much easier. 
Home-page: https://github.com/brianlan/copious
Author: brianlan
Author-email: brianlanbo@gmail.com
Requires-Dist: numpy>=1.22
Requires-Dist: scipy>=1.8
Requires-Dist: tqdm>=4.62
Requires-Dist: matplotlib>=3.5
Requires-Dist: pyyaml>=6.0
Requires-Dist: opencv-python>=4.6
Requires-Dist: polars>=0.20
Requires-Dist: pypcd4>=1.0
Provides-Extra: dev
Requires-Dist: pytest>=7.0.0; extra == "dev"
Requires-Dist: twine; extra == "dev"
Dynamic: author
Dynamic: author-email
Dynamic: description
Dynamic: description-content-type
Dynamic: home-page
Dynamic: provides-extra
Dynamic: requires-dist
Dynamic: summary
